testcontainers/compose/__init__.py
testcontainers/compose/compose.py
testcontainers/core/__init__.py
testcontainers/core/auth.py
testcontainers/core/config.py
testcontainers/core/container.py
testcontainers/core/docker_client.py
testcontainers/core/exceptions.py
testcontainers/core/generic.py
testcontainers/core/image.py
testcontainers/core/labels.py
testcontainers/core/network.py
testcontainers/core/utils.py
testcontainers/core/version.py
testcontainers/core/waiting_utils.py
testcontainers/socat/__init__.py
testcontainers/socat/socat.py
testcontainers/arangodb/__init__.py
testcontainers/aws/__init__.py
testcontainers/aws/aws_lambda.py
testcontainers/azurite/__init__.py
testcontainers/cassandra/__init__.py
testcontainers/chroma/__init__.py
testcontainers/clickhouse/__init__.py
testcontainers/cockroachdb/__init__.py
testcontainers/cosmosdb/__init__.py
testcontainers/cosmosdb/_emulator.py
testcontainers/cosmosdb/_grab.py
testcontainers/cosmosdb/mongodb.py
testcontainers/cosmosdb/nosql.py
testcontainers/db2/__init__.py
testcontainers/elasticsearch/__init__.py
testcontainers/generic/__init__.py
testcontainers/generic/server.py
testcontainers/google/__init__.py
testcontainers/google/datastore.py
testcontainers/google/pubsub.py
testcontainers/influxdb.py
testcontainers/influxdb1/__init__.py
testcontainers/influxdb2/__init__.py
testcontainers/k3s/__init__.py
testcontainers/kafka/__init__.py
testcontainers/kafka/_redpanda.py
testcontainers/keycloak/__init__.py
testcontainers/localstack/__init__.py
testcontainers/mailpit/__init__.py
testcontainers/mailpit/py.typed
testcontainers/memcached/__init__.py
testcontainers/milvus/__init__.py
testcontainers/minio/__init__.py
testcontainers/mongodb/__init__.py
testcontainers/mqtt/__init__.py
testcontainers/mqtt/testcontainers-mosquitto-default-configuration.conf
testcontainers/mssql/__init__.py
testcontainers/mysql/__init__.py
testcontainers/nats/__init__.py
testcontainers/neo4j/__init__.py
testcontainers/nginx/__init__.py
testcontainers-4.11.0.dist-info/LICENSE.txt
testcontainers-4.11.0.dist-info/METADATA
testcontainers-4.11.0.dist-info/WHEEL
testcontainers-4.11.0.dist-info/RECORD
