Metadata-Version: 2.3
Name: testcontainers
Version: 4.11.0
Summary: Python library for throwaway instances of anything that can run in a Docker container
Keywords: testing,logging,docker,test automation
Author: Sergey Pirogov
Author-email: automationremarks@gmail.com
Maintainer: Balint Bartha
Maintainer-email: totallyzen@users.noreply.github.com
Requires-Python: >=3.9,<4.0
Classifier: Intended Audience :: Developers
Classifier: Intended Audience :: Information Technology
Classifier: License :: OSI Approved :: Apache Software License
Classifier: Operating System :: MacOS
Classifier: Operating System :: Microsoft :: Windows
Classifier: Operating System :: POSIX
Classifier: Operating System :: Unix
Classifier: Programming Language :: Python :: 3
Classifier: Programming Language :: Python :: 3.9
Classifier: Programming Language :: Python :: 3.10
Classifier: Programming Language :: Python :: 3.11
Classifier: Programming Language :: Python :: 3.12
Classifier: Programming Language :: Python :: 3.13
Classifier: Topic :: Software Development :: Libraries :: Python Modules
Provides-Extra: arangodb
Provides-Extra: aws
Provides-Extra: azurite
Provides-Extra: cassandra
Provides-Extra: chroma
Provides-Extra: clickhouse
Provides-Extra: cockroachdb
Provides-Extra: cosmosdb
Provides-Extra: db2
Provides-Extra: elasticsearch
Provides-Extra: generic
Provides-Extra: google
Provides-Extra: influxdb
Provides-Extra: k3s
Provides-Extra: kafka
Provides-Extra: keycloak
Provides-Extra: localstack
Provides-Extra: mailpit
Provides-Extra: memcached
Provides-Extra: milvus
Provides-Extra: minio
Provides-Extra: mongodb
Provides-Extra: mqtt
Provides-Extra: mssql
Provides-Extra: mysql
Provides-Extra: nats
Provides-Extra: neo4j
Provides-Extra: nginx
Provides-Extra: ollama
Provides-Extra: opensearch
Provides-Extra: oracle
Provides-Extra: oracle-free
Provides-Extra: postgres
Provides-Extra: qdrant
Provides-Extra: rabbitmq
Provides-Extra: redis
Provides-Extra: registry
Provides-Extra: scylla
Provides-Extra: selenium
Provides-Extra: sftp
Provides-Extra: test-module-import
Provides-Extra: trino
Provides-Extra: vault
Provides-Extra: weaviate
Requires-Dist: azure-cosmos ; extra == "cosmosdb"
Requires-Dist: azure-storage-blob (>=12.19,<13.0) ; extra == "azurite"
Requires-Dist: bcrypt ; extra == "registry"
Requires-Dist: boto3 ; extra == "aws" or extra == "localstack"
Requires-Dist: cassandra-driver (==3.29.1) ; extra == "scylla"
Requires-Dist: chromadb-client (>=1.0.0,<2.0.0) ; extra == "chroma"
Requires-Dist: clickhouse-driver ; extra == "clickhouse"
Requires-Dist: cryptography ; extra == "mailpit" or extra == "sftp"
Requires-Dist: docker
Requires-Dist: google-cloud-datastore (>=2) ; extra == "google"
Requires-Dist: google-cloud-pubsub (>=2) ; extra == "google"
Requires-Dist: httpx ; extra == "aws" or extra == "generic" or extra == "test-module-import"
Requires-Dist: ibm_db_sa ; (platform_machine != "aarch64" and platform_machine != "arm64") and (extra == "db2")
Requires-Dist: influxdb ; extra == "influxdb"
Requires-Dist: influxdb-client ; extra == "influxdb"
Requires-Dist: kubernetes ; extra == "k3s"
Requires-Dist: minio ; extra == "minio"
Requires-Dist: nats-py ; extra == "nats"
Requires-Dist: neo4j ; extra == "neo4j"
Requires-Dist: opensearch-py ; extra == "opensearch"
Requires-Dist: oracledb ; extra == "oracle" or extra == "oracle-free"
Requires-Dist: pika ; extra == "rabbitmq"
Requires-Dist: pymongo ; extra == "mongodb"
Requires-Dist: pymssql ; extra == "mssql"
Requires-Dist: pymysql[rsa] ; extra == "mysql"
Requires-Dist: python-arango (>=7.8,<8.0) ; extra == "arangodb"
Requires-Dist: python-dotenv
Requires-Dist: python-keycloak ; extra == "keycloak"
Requires-Dist: pyyaml ; extra == "k3s"
Requires-Dist: qdrant-client ; extra == "qdrant"
Requires-Dist: redis ; extra == "generic" or extra == "redis"
Requires-Dist: selenium ; extra == "selenium"
Requires-Dist: sqlalchemy ; extra == "db2" or extra == "mssql" or extra == "mysql" or extra == "oracle" or extra == "oracle-free"
Requires-Dist: trino ; extra == "trino"
Requires-Dist: typing-extensions
Requires-Dist: urllib3
Requires-Dist: weaviate-client (>=4.5.4,<5.0.0) ; extra == "weaviate"
Requires-Dist: wrapt
Project-URL: GitHub, https://github.com/testcontainers/testcontainers-python
Project-URL: Issue Tracker, https://github.com/testcontainers/testcontainers-python/issues
